spectrogram_to_audio/__init__.py
spectrogram_to_audio/config/__init__.py
spectrogram_to_audio/config/config_files/config-default.yaml
spectrogram_to_audio/config/load_config.py
spectrogram_to_audio/data_preprocessing/__init__.py
spectrogram_to_audio/data_preprocessing/dataset.py
spectrogram_to_audio/tests/__init__.py
spectrogram_to_audio/tests/audios/7a59c34a-2f32-48d0-9897-644bbc2dec07_no_hash_10676-11676.wav
spectrogram_to_audio/tests/audios/7a59c34a-2f32-48d0-9897-644bbc2dec07_no_hash_16843-17843.wav
spectrogram_to_audio/tests/audios/7a59c34a-2f32-48d0-9897-644bbc2dec07_no_hash_19778-20778.wav
spectrogram_to_audio/tests/audios/7a59c34a-2f32-48d0-9897-644bbc2dec07_no_hash_22747-23747.wav
spectrogram_to_audio/tests/audios/7a59c34a-2f32-48d0-9897-644bbc2dec07_no_hash_26510-27510.wav
spectrogram_to_audio/tests/audios/7a59c34a-2f32-48d0-9897-644bbc2dec07_no_hash_32603-33603.wav
spectrogram_to_audio/tests/audios/7a59c34a-2f32-48d0-9897-644bbc2dec07_no_hash_3459-4459.wav
spectrogram_to_audio/tests/audios/7a59c34a-2f32-48d0-9897-644bbc2dec07_no_hash_35291-36291.wav
spectrogram_to_audio/tests/audios/7a59c34a-2f32-48d0-9897-644bbc2dec07_no_hash_38465-39465.wav
spectrogram_to_audio/tests/test_dataset_generation.py
spectrogram_to_audio/tests/test_resize_audio.py
spectrogram_to_audio/train.py
spectrogram_to_audio-0.0.5.dist-info/WHEEL
spectrogram_to_audio-0.0.5.dist-info/METADATA
spectrogram_to_audio-0.0.5.dist-info/RECORD
