Metadata-Version: 2.1
Name: spectrogram-to-audio
Version: 0.0.5
Summary: 
Author: carl2g
Author-email: degentilecarl@gmail.com
Requires-Python: >=3.6,<3.9
Classifier: Programming Language :: Python :: 3
Classifier: Programming Language :: Python :: 3.6
Classifier: Programming Language :: Python :: 3.7
Classifier: Programming Language :: Python :: 3.8
Requires-Dist: dynaconf (>=3.1.2,<4.0.0)
Requires-Dist: tensorflow (>=2.3.1,<3.0.0)
Requires-Dist: tensorflow-addons (>=0.11.2,<0.12.0)
Requires-Dist: tensorflow-datasets (>=4.1.0,<5.0.0)
Requires-Dist: tensorflow-io (>=0.16.0,<0.17.0)
